{
  "columns": [
    "Player 1",
    "Unnamed: 1",
    "Unnamed: 2",
    "Unnamed: 3",
    "Player 2",
    "Unnamed: 5",
    "Unnamed: 6",
    "Unnamed: 7",
    "Unnamed: 8",
    "Unnamed: 9",
    "Unnamed: 10",
    "Unnamed: 11",
    "Unnamed: 12",
    "Unnamed: 13"
  ],
  "rows": [
    {
      "Player 1": "Alec Bohm",
      "Unnamed: 1": "=DISPIMG(\"ID_EE542ED63BBA41B1BF1A0E624107DB19\",1)",
      "Unnamed: 2": "",
      "Unnamed: 3": "",
      "Player 2": "Nolan Arenado",
      "Unnamed: 5": "=DISPIMG(\"ID_2ED6508171C647D19EACFF2F49EA26FA\",1)",
      "Unnamed: 6": "",
      "Unnamed: 7": "",
      "Unnamed: 8": "",
      "Unnamed: 9": "Postions",
      "Unnamed: 10": "",
      "Unnamed: 11": "",
      "Unnamed: 12": "",
      "Unnamed: 13": ""
    },
    {
      "Player 1": "",
      "Unnamed: 1": "",
      "Unnamed: 2": "",
      "Unnamed: 3": "",
      "Player 2": "",
      "Unnamed: 5": "",
      "Unnamed: 6": "",
      "Unnamed: 7": "",
      "Unnamed: 8": "",
      "Unnamed: 9": "3B",
      "Unnamed: 10": "Name",
      "Unnamed: 11": "Pos",
      "Unnamed: 12": "Age",
      "Unnamed: 13": ""
    },
    {
      "Player 1": "Postion",
      "Unnamed: 1": "3B",
      "Unnamed: 2": "",
      "Unnamed: 3": "",
      "Player 2": "Postion",
      "Unnamed: 5": "3B",
      "Unnamed: 6": "",
      "Unnamed: 7": "",
      "Unnamed: 8": "",
      "Unnamed: 9": "",
      "Unnamed: 10": "Nolan Arenado",
      "Unnamed: 11": "3B",
      "Unnamed: 12": 34,
      "Unnamed: 13": "=DISPIMG(\"ID_2ED6508171C647D19EACFF2F49EA26FA\",1)"
    },
    {
      "Player 1": "Age",
      "Unnamed: 1": 29,
      "Unnamed: 2": "",
      "Unnamed: 3": "",
      "Player 2": "",
      "Unnamed: 5": 34,
      "Unnamed: 6": "",
      "Unnamed: 7": "",
      "Unnamed: 8": "",
      "Unnamed: 9": "",
      "Unnamed: 10": "Alec Bohm",
      "Unnamed: 11": "3B",
      "Unnamed: 12": 29,
      "Unnamed: 13": "=DISPIMG(\"ID_EE542ED63BBA41B1BF1A0E624107DB19\",1)"
    },
    {
      "Player 1": "Bat Handess",
      "Unnamed: 1": "Right",
      "Unnamed: 2": "",
      "Unnamed: 3": "",
      "Player 2": "Bat Handess",
      "Unnamed: 5": "Right",
      "Unnamed: 6": "",
      "Unnamed: 7": "",
      "Unnamed: 8": "",
      "Unnamed: 9": "",
      "Unnamed: 10": "",
      "Unnamed: 11": "",
      "Unnamed: 12": "",
      "Unnamed: 13": 0
    },
    {
      "Player 1": "Games Played %",
      "Unnamed: 1": 0.740740740740741,
      "Unnamed: 2": "",
      "Unnamed: 3": "",
      "Player 2": "Games Played %",
      "Unnamed: 5": 0.660493827160494,
      "Unnamed: 6": "",
      "Unnamed: 7": "",
      "Unnamed: 8": "",
      "Unnamed: 9": "",
      "Unnamed: 10": "",
      "Unnamed: 11": "",
      "Unnamed: 12": "",
      "Unnamed: 13": 0
    },
    {
      "Player 1": "Doubles",
      "Unnamed: 1": 18,
      "Unnamed: 2": "",
      "Unnamed: 3": "",
      "Player 2": "Doubles",
      "Unnamed: 5": 18,
      "Unnamed: 6": "",
      "Unnamed: 7": "",
      "Unnamed: 8": "",
      "Unnamed: 9": "",
      "Unnamed: 10": "",
      "Unnamed: 11": "",
      "Unnamed: 12": "",
      "Unnamed: 13": 0
    },
    {
      "Player 1": "Home Runs",
      "Unnamed: 1": 11,
      "Unnamed: 2": "",
      "Unnamed: 3": "",
      "Player 2": "Home Runs",
      "Unnamed: 5": 12,
      "Unnamed: 6": "",
      "Unnamed: 7": "",
      "Unnamed: 8": "",
      "Unnamed: 9": "",
      "Unnamed: 10": "",
      "Unnamed: 11": "",
      "Unnamed: 12": "",
      "Unnamed: 13": 0
    },
    {
      "Player 1": "RBI's",
      "Unnamed: 1": 59,
      "Unnamed: 2": "",
      "Unnamed: 3": "",
      "Player 2": "RBI's",
      "Unnamed: 5": 52,
      "Unnamed: 6": "",
      "Unnamed: 7": "",
      "Unnamed: 8": "",
      "Unnamed: 9": "",
      "Unnamed: 10": "",
      "Unnamed: 11": "",
      "Unnamed: 12": "",
      "Unnamed: 13": ""
    },
    {
      "Player 1": "Walk Rate",
      "Unnamed: 1": 0.0575396825396825,
      "Unnamed: 2": "",
      "Unnamed: 3": "",
      "Player 2": "Walk Rate",
      "Unnamed: 5": 0.0642201834862385,
      "Unnamed: 6": "",
      "Unnamed: 7": "",
      "Unnamed: 8": "",
      "Unnamed: 9": "",
      "Unnamed: 10": "",
      "Unnamed: 11": "",
      "Unnamed: 12": "",
      "Unnamed: 13": ""
    },
    {
      "Player 1": "K Rate",
      "Unnamed: 1": 0.162698412698413,
      "Unnamed: 2": "",
      "Unnamed: 3": "",
      "Player 2": "K Rate",
      "Unnamed: 5": 0.112385321100917,
      "Unnamed: 6": "",
      "Unnamed: 7": "",
      "Unnamed: 8": "",
      "Unnamed: 9": "",
      "Unnamed: 10": "",
      "Unnamed: 11": "",
      "Unnamed: 12": "",
      "Unnamed: 13": ""
    },
    {
      "Player 1": "Avg",
      "Unnamed: 1": 0.287,
      "Unnamed: 2": "",
      "Unnamed: 3": "",
      "Player 2": "Avg",
      "Unnamed: 5": 0.237,
      "Unnamed: 6": "",
      "Unnamed: 7": "",
      "Unnamed: 8": "",
      "Unnamed: 9": "",
      "Unnamed: 10": "",
      "Unnamed: 11": "",
      "Unnamed: 12": "",
      "Unnamed: 13": ""
    },
    {
      "Player 1": "OPS",
      "Unnamed: 1": 0.741,
      "Unnamed: 2": "",
      "Unnamed: 3": "",
      "Player 2": "OPS",
      "Unnamed: 5": 0.666,
      "Unnamed: 6": "",
      "Unnamed: 7": "",
      "Unnamed: 8": "",
      "Unnamed: 9": "",
      "Unnamed: 10": "",
      "Unnamed: 11": "",
      "Unnamed: 12": "",
      "Unnamed: 13": ""
    },
    {
      "Player 1": "OPS+",
      "Unnamed: 1": 102,
      "Unnamed: 2": "",
      "Unnamed: 3": "",
      "Player 2": "OPS+",
      "Unnamed: 5": 87,
      "Unnamed: 6": "",
      "Unnamed: 7": "",
      "Unnamed: 8": "",
      "Unnamed: 9": "",
      "Unnamed: 10": "",
      "Unnamed: 11": "",
      "Unnamed: 12": "",
      "Unnamed: 13": ""
    },
    {
      "Player 1": "OPS Vs RHP",
      "Unnamed: 1": 0.713,
      "Unnamed: 2": "",
      "Unnamed: 3": "",
      "Player 2": "OPS Vs RHP",
      "Unnamed: 5": 0.639,
      "Unnamed: 6": "",
      "Unnamed: 7": "",
      "Unnamed: 8": "",
      "Unnamed: 9": "",
      "Unnamed: 10": "",
      "Unnamed: 11": "",
      "Unnamed: 12": "",
      "Unnamed: 13": ""
    },
    {
      "Player 1": "OPS Vs LHP",
      "Unnamed: 1": 0.818,
      "Unnamed: 2": "",
      "Unnamed: 3": "",
      "Player 2": "OPS Vs LHP",
      "Unnamed: 5": 0.741,
      "Unnamed: 6": "",
      "Unnamed: 7": "",
      "Unnamed: 8": "",
      "Unnamed: 9": "",
      "Unnamed: 10": "",
      "Unnamed: 11": "",
      "Unnamed: 12": "",
      "Unnamed: 13": ""
    }
  ]
}